{"primaryContentSections":[{"kind":"declarations","declarations":[{"platforms":["Linux"],"languages":["swift"],"tokens":[{"kind":"keyword","text":"static"},{"kind":"text","text":" "},{"kind":"keyword","text":"func"},{"kind":"text","text":" "},{"kind":"identifier","text":"buildBlock"},{"kind":"text","text":"<"},{"kind":"genericParameter","text":"P0"},{"kind":"text","text":", "},{"kind":"genericParameter","text":"P1"},{"kind":"text","text":", "},{"kind":"genericParameter","text":"P2"},{"kind":"text","text":", "},{"kind":"genericParameter","text":"P3"},{"kind":"text","text":", "},{"kind":"genericParameter","text":"P4"},{"kind":"text","text":", "},{"kind":"genericParameter","text":"P5"},{"kind":"text","text":">("},{"kind":"externalParam","text":"_"},{"kind":"text","text":" "},{"kind":"internalParam","text":"p0"},{"kind":"text","text":": "},{"kind":"typeIdentifier","text":"P0"},{"kind":"text","text":", "},{"kind":"externalParam","text":"_"},{"kind":"text","text":" "},{"kind":"internalParam","text":"p1"},{"kind":"text","text":": "},{"kind":"typeIdentifier","text":"P1"},{"kind":"text","text":", "},{"kind":"externalParam","text":"_"},{"kind":"text","text":" "},{"kind":"internalParam","text":"p2"},{"kind":"text","text":": "},{"kind":"typeIdentifier","text":"P2"},{"kind":"text","text":", "},{"kind":"externalParam","text":"_"},{"kind":"text","text":" "},{"kind":"internalParam","text":"p3"},{"kind":"text","text":": "},{"kind":"typeIdentifier","text":"P3"},{"kind":"text","text":", "},{"kind":"externalParam","text":"_"},{"kind":"text","text":" "},{"kind":"internalParam","text":"p4"},{"kind":"text","text":": "},{"kind":"typeIdentifier","text":"P4"},{"kind":"text","text":", "},{"kind":"externalParam","text":"_"},{"kind":"text","text":" "},{"kind":"internalParam","text":"p5"},{"kind":"text","text":": "},{"kind":"typeIdentifier","text":"P5"},{"kind":"text","text":") -> "},{"kind":"typeIdentifier","identifier":"doc:\/\/co.pointfree.VaporRouting\/documentation\/URLRouting\/PathZipOVOVOO","text":"PathZipOVOVOO","preciseIdentifier":"s:10URLRouting13PathZipOVOVOOV"},{"kind":"text","text":"<"},{"kind":"typeIdentifier","text":"P0"},{"kind":"text","text":", "},{"kind":"typeIdentifier","text":"P1"},{"kind":"text","text":", "},{"kind":"typeIdentifier","text":"P2"},{"kind":"text","text":", "},{"kind":"typeIdentifier","text":"P3"},{"kind":"text","text":", "},{"kind":"typeIdentifier","text":"P4"},{"kind":"text","text":", "},{"kind":"typeIdentifier","text":"P5"},{"kind":"text","text":"> "},{"kind":"keyword","text":"where"},{"kind":"text","text":" "},{"kind":"typeIdentifier","text":"P0"},{"kind":"text","text":" : "},{"kind":"typeIdentifier","identifier":"doc:\/\/co.pointfree.VaporRouting\/documentation\/Parsing\/Parser","text":"Parser","preciseIdentifier":"s:7Parsing6ParserP"},{"kind":"text","text":", "},{"kind":"typeIdentifier","text":"P1"},{"kind":"text","text":" : "},{"kind":"typeIdentifier","identifier":"doc:\/\/co.pointfree.VaporRouting\/documentation\/Parsing\/Parser","text":"Parser","preciseIdentifier":"s:7Parsing6ParserP"},{"kind":"text","text":", "},{"kind":"typeIdentifier","text":"P2"},{"kind":"text","text":" : "},{"kind":"typeIdentifier","identifier":"doc:\/\/co.pointfree.VaporRouting\/documentation\/Parsing\/Parser","text":"Parser","preciseIdentifier":"s:7Parsing6ParserP"},{"kind":"text","text":", "},{"kind":"typeIdentifier","text":"P3"},{"kind":"text","text":" : "},{"kind":"typeIdentifier","identifier":"doc:\/\/co.pointfree.VaporRouting\/documentation\/Parsing\/Parser","text":"Parser","preciseIdentifier":"s:7Parsing6ParserP"},{"kind":"text","text":", "},{"kind":"typeIdentifier","text":"P4"},{"kind":"text","text":" : "},{"kind":"typeIdentifier","identifier":"doc:\/\/co.pointfree.VaporRouting\/documentation\/Parsing\/Parser","text":"Parser","preciseIdentifier":"s:7Parsing6ParserP"},{"kind":"text","text":", "},{"kind":"typeIdentifier","text":"P5"},{"kind":"text","text":" : "},{"kind":"typeIdentifier","identifier":"doc:\/\/co.pointfree.VaporRouting\/documentation\/Parsing\/Parser","text":"Parser","preciseIdentifier":"s:7Parsing6ParserP"},{"kind":"text","text":", "},{"kind":"typeIdentifier","text":"P0"},{"kind":"text","text":"."},{"kind":"typeIdentifier","text":"Input"},{"kind":"text","text":" == "},{"kind":"typeIdentifier","text":"Substring","preciseIdentifier":"s:Ss"},{"kind":"text","text":", "},{"kind":"typeIdentifier","text":"P1"},{"kind":"text","text":"."},{"kind":"typeIdentifier","text":"Input"},{"kind":"text","text":" == "},{"kind":"typeIdentifier","text":"Substring","preciseIdentifier":"s:Ss"},{"kind":"text","text":", "},{"kind":"typeIdentifier","text":"P1"},{"kind":"text","text":"."},{"kind":"typeIdentifier","text":"Output"},{"kind":"text","text":" == "},{"kind":"typeIdentifier","text":"Void","preciseIdentifier":"s:s4Voida"},{"kind":"text","text":", "},{"kind":"typeIdentifier","text":"P2"},{"kind":"text","text":"."},{"kind":"typeIdentifier","text":"Input"},{"kind":"text","text":" == "},{"kind":"typeIdentifier","text":"Substring","preciseIdentifier":"s:Ss"},{"kind":"text","text":", "},{"kind":"typeIdentifier","text":"P3"},{"kind":"text","text":"."},{"kind":"typeIdentifier","text":"Input"},{"kind":"text","text":" == "},{"kind":"typeIdentifier","text":"Substring","preciseIdentifier":"s:Ss"},{"kind":"text","text":", "},{"kind":"typeIdentifier","text":"P3"},{"kind":"text","text":"."},{"kind":"typeIdentifier","text":"Output"},{"kind":"text","text":" == "},{"kind":"typeIdentifier","text":"Void","preciseIdentifier":"s:s4Voida"},{"kind":"text","text":", "},{"kind":"typeIdentifier","text":"P4"},{"kind":"text","text":"."},{"kind":"typeIdentifier","text":"Input"},{"kind":"text","text":" == "},{"kind":"typeIdentifier","text":"Substring","preciseIdentifier":"s:Ss"},{"kind":"text","text":", "},{"kind":"typeIdentifier","text":"P5"},{"kind":"text","text":"."},{"kind":"typeIdentifier","text":"Input"},{"kind":"text","text":" == "},{"kind":"typeIdentifier","text":"Substring","preciseIdentifier":"s:Ss"}]}]}],"identifier":{"url":"doc:\/\/co.pointfree.VaporRouting\/documentation\/URLRouting\/PathBuilder\/buildBlock(_:_:_:_:_:_:)-11ijy","interfaceLanguage":"swift"},"metadata":{"role":"symbol","modules":[{"name":"URLRouting"}],"externalID":"s:10URLRouting11PathBuilderO10buildBlockyAA0B9ZipOVOVOOVyxq_q0_q1_q2_q3_Gx_q_q0_q1_q2_q3_t7Parsing6ParserRzAhIR_AhIR0_AhIR1_AhIR2_AhIR3_Ss5InputRtzSsAJRt_yt6OutputRt_SsAJRt0_SsAJRt1_ytAMRt1_SsAJRt2_SsAJRt3_r4_lFZ","title":"buildBlock(_:_:_:_:_:_:)","roleHeading":"Type Method","symbolKind":"method","extendedModule":"URLRouting","fragments":[{"kind":"keyword","text":"static"},{"kind":"text","text":" "},{"kind":"keyword","text":"func"},{"kind":"text","text":" "},{"kind":"identifier","text":"buildBlock"},{"kind":"text","text":"<"},{"kind":"genericParameter","text":"P0"},{"kind":"text","text":", "},{"kind":"genericParameter","text":"P1"},{"kind":"text","text":", "},{"kind":"genericParameter","text":"P2"},{"kind":"text","text":", "},{"kind":"genericParameter","text":"P3"},{"kind":"text","text":", "},{"kind":"genericParameter","text":"P4"},{"kind":"text","text":", "},{"kind":"genericParameter","text":"P5"},{"kind":"text","text":">("},{"kind":"typeIdentifier","text":"P0"},{"kind":"text","text":", "},{"kind":"typeIdentifier","text":"P1"},{"kind":"text","text":", "},{"kind":"typeIdentifier","text":"P2"},{"kind":"text","text":", "},{"kind":"typeIdentifier","text":"P3"},{"kind":"text","text":", "},{"kind":"typeIdentifier","text":"P4"},{"kind":"text","text":", "},{"kind":"typeIdentifier","text":"P5"},{"kind":"text","text":") -> "},{"preciseIdentifier":"s:10URLRouting13PathZipOVOVOOV","kind":"typeIdentifier","text":"PathZipOVOVOO"},{"kind":"text","text":"<"},{"kind":"typeIdentifier","text":"P0"},{"kind":"text","text":", "},{"kind":"typeIdentifier","text":"P1"},{"kind":"text","text":", "},{"kind":"typeIdentifier","text":"P2"},{"kind":"text","text":", "},{"kind":"typeIdentifier","text":"P3"},{"kind":"text","text":", "},{"kind":"typeIdentifier","text":"P4"},{"kind":"text","text":", "},{"kind":"typeIdentifier","text":"P5"},{"kind":"text","text":">"}]},"hierarchy":{"paths":[["doc:\/\/co.pointfree.VaporRouting\/documentation\/URLRouting","doc:\/\/co.pointfree.VaporRouting\/documentation\/URLRouting\/PathBuilder"]]},"sections":[],"kind":"symbol","variants":[{"paths":["\/documentation\/urlrouting\/pathbuilder\/buildblock(_:_:_:_:_:_:)-11ijy"],"traits":[{"interfaceLanguage":"swift"}]}],"schemaVersion":{"minor":3,"major":0,"patch":0},"references":{"doc://co.pointfree.VaporRouting/documentation/URLRouting/PathZipOVOVOO":{"kind":"symbol","type":"topic","navigatorTitle":[{"text":"PathZipOVOVOO","kind":"identifier"}],"abstract":[],"role":"symbol","fragments":[{"text":"struct","kind":"keyword"},{"text":" ","kind":"text"},{"text":"PathZipOVOVOO","kind":"identifier"}],"url":"\/documentation\/urlrouting\/pathzipovovoo","identifier":"doc:\/\/co.pointfree.VaporRouting\/documentation\/URLRouting\/PathZipOVOVOO","title":"PathZipOVOVOO"},"doc://co.pointfree.VaporRouting/documentation/URLRouting/PathBuilder/buildBlock(_:_:_:_:_:_:)-11ijy":{"role":"symbol","identifier":"doc:\/\/co.pointfree.VaporRouting\/documentation\/URLRouting\/PathBuilder\/buildBlock(_:_:_:_:_:_:)-11ijy","title":"buildBlock(_:_:_:_:_:_:)","url":"\/documentation\/urlrouting\/pathbuilder\/buildblock(_:_:_:_:_:_:)-11ijy","fragments":[{"text":"static","kind":"keyword"},{"text":" ","kind":"text"},{"kind":"keyword","text":"func"},{"kind":"text","text":" "},{"kind":"identifier","text":"buildBlock"},{"kind":"text","text":"<"},{"kind":"genericParameter","text":"P0"},{"kind":"text","text":", "},{"text":"P1","kind":"genericParameter"},{"text":", ","kind":"text"},{"text":"P2","kind":"genericParameter"},{"text":", ","kind":"text"},{"text":"P3","kind":"genericParameter"},{"text":", ","kind":"text"},{"text":"P4","kind":"genericParameter"},{"text":", ","kind":"text"},{"text":"P5","kind":"genericParameter"},{"text":">(","kind":"text"},{"text":"P0","kind":"typeIdentifier"},{"text":", ","kind":"text"},{"text":"P1","kind":"typeIdentifier"},{"text":", ","kind":"text"},{"text":"P2","kind":"typeIdentifier"},{"text":", ","kind":"text"},{"text":"P3","kind":"typeIdentifier"},{"text":", ","kind":"text"},{"text":"P4","kind":"typeIdentifier"},{"text":", ","kind":"text"},{"text":"P5","kind":"typeIdentifier"},{"text":") -> ","kind":"text"},{"text":"PathZipOVOVOO","kind":"typeIdentifier","preciseIdentifier":"s:10URLRouting13PathZipOVOVOOV"},{"text":"<","kind":"text"},{"text":"P0","kind":"typeIdentifier"},{"text":", ","kind":"text"},{"text":"P1","kind":"typeIdentifier"},{"text":", ","kind":"text"},{"text":"P2","kind":"typeIdentifier"},{"text":", ","kind":"text"},{"text":"P3","kind":"typeIdentifier"},{"text":", ","kind":"text"},{"text":"P4","kind":"typeIdentifier"},{"text":", ","kind":"text"},{"text":"P5","kind":"typeIdentifier"},{"text":">","kind":"text"}],"kind":"symbol","type":"topic","abstract":[]},"doc://co.pointfree.VaporRouting/documentation/URLRouting/PathBuilder":{"fragments":[{"kind":"keyword","text":"enum"},{"kind":"text","text":" "},{"kind":"identifier","text":"PathBuilder"}],"identifier":"doc:\/\/co.pointfree.VaporRouting\/documentation\/URLRouting\/PathBuilder","type":"topic","kind":"symbol","url":"\/documentation\/urlrouting\/pathbuilder","navigatorTitle":[{"kind":"identifier","text":"PathBuilder"}],"title":"PathBuilder","abstract":[],"role":"symbol"},"doc://co.pointfree.VaporRouting/documentation/URLRouting":{"url":"\/documentation\/urlrouting","title":"URLRouting","identifier":"doc:\/\/co.pointfree.VaporRouting\/documentation\/URLRouting","abstract":[],"role":"collection","kind":"symbol","type":"topic"},"doc://co.pointfree.VaporRouting/documentation/Parsing/Parser":{"type":"topic","role":"symbol","kind":"symbol","abstract":[{"type":"text","text":"Declares a type that can incrementally parse an "},{"code":"Output","type":"codeVoice"},{"type":"text","text":" value from an "},{"code":"Input","type":"codeVoice"},{"type":"text","text":" value."}],"title":"Parser","identifier":"doc:\/\/co.pointfree.VaporRouting\/documentation\/Parsing\/Parser","fragments":[{"kind":"keyword","text":"protocol"},{"kind":"text","text":" "},{"kind":"identifier","text":"Parser"}],"navigatorTitle":[{"kind":"identifier","text":"Parser"}],"url":"\/documentation\/parsing\/parser"}}}